purpleair_client/__init__.py
purpleair_client/client.py
purpleair_client/models.py
purpleair_client-0.1.1.dist-info/LICENSE
purpleair_client-0.1.1.dist-info/METADATA
purpleair_client-0.1.1.dist-info/WHEEL
purpleair_client-0.1.1.dist-info/RECORD
