Metadata-Version: 2.1
Name: purpleair-client
Version: 0.1.1
Summary: System for fetching, storing and displaying air quality data from PurpleAir
License: MIT
Author: Valentina Hernandez
Author-email: vahernandezmo@gmail.com
Requires-Python: >=3.8,<3.13
Classifier: License :: OSI Approved :: MIT License
Classifier: Programming Language :: Python :: 3
Classifier: Programming Language :: Python :: 3.8
Classifier: Programming Language :: Python :: 3.9
Classifier: Programming Language :: Python :: 3.10
Classifier: Programming Language :: Python :: 3.11
Classifier: Programming Language :: Python :: 3.12
Requires-Dist: requests (>=2.32.3,<3.0.0)
